pysvgo/__init__.py
pysvgo/_read.py
pysvgo/addition.py
pysvgo/core.py
pysvgo/default.py
pysvgo/main.py
pysvgo/multiplication.py
pysvgo-0.0.1.dist-info/LICENSE
pysvgo-0.0.1.dist-info/METADATA
pysvgo-0.0.1.dist-info/WHEEL
pysvgo-0.0.1.dist-info/top_level.txt
pysvgo-0.0.1.dist-info/zip-safe
pysvgo-0.0.1.dist-info/RECORD
