Metadata-Version: 2.1
Name: pysvgo
Version: 0.0.1
Summary: SVG optimizer
Home-page: UNKNOWN
Author: René Horn
Author-email: rene_horn@gmx.net
License: MIT License
Platform: UNKNOWN
Classifier: Programming Language :: Python :: 3
Classifier: License :: OSI Approved :: MIT License
Classifier: Operating System :: OS Independent
Classifier: Development Status :: 5 - Production/Stable
Requires-Python: >=3.7
License-File: LICENSE
Provides-Extra: testing
Requires-Dist: pytest (>=6.0) ; extra == 'testing'
Requires-Dist: pytest-cov (>=2.0) ; extra == 'testing'
Requires-Dist: mypy (>=0.9.10) ; extra == 'testing'
Requires-Dist: flake8 (>=3.9) ; extra == 'testing'
Requires-Dist: tox (>=3.24) ; extra == 'testing'
Requires-Dist: sphinx ; extra == 'testing'
Requires-Dist: sphinx-rtd-theme ; extra == 'testing'
Requires-Dist: sphinxcontrib-napoleon ; extra == 'testing'
